fastapi_healthchecks/__init__.py
fastapi_healthchecks/api/__init__.py
fastapi_healthchecks/api/models.py
fastapi_healthchecks/api/router.py
fastapi_healthchecks/checks/__init__.py
fastapi_healthchecks/checks/_base.py
fastapi_healthchecks/checks/ceph.py
fastapi_healthchecks/checks/http.py
fastapi_healthchecks/checks/postgres.py
fastapi_healthchecks/checks/rabbit_mq.py
fastapi_healthchecks/checks/redis.py
fastapi_healthchecks/checks/settings.py
fastapi_healthchecks-1.1.0.dist-info/LICENSE
fastapi_healthchecks-1.1.0.dist-info/METADATA
fastapi_healthchecks-1.1.0.dist-info/WHEEL
fastapi_healthchecks-1.1.0.dist-info/RECORD
