Metadata-Version: 2.1
Name: fastapi-healthchecks
Version: 1.1.0
Summary: FastAPI Healthchecks
License: MIT
Keywords: fastapi,healthcheck
Author: RockITSoft
Requires-Python: >=3.10,<4.0
Classifier: License :: OSI Approved :: MIT License
Classifier: Programming Language :: Python :: 3
Classifier: Programming Language :: Python :: 3.10
Classifier: Programming Language :: Python :: 3.11
Classifier: Programming Language :: Python :: 3.12
Provides-Extra: all
Provides-Extra: ceph
Provides-Extra: http
Provides-Extra: postgres
Provides-Extra: rabbitmq
Provides-Extra: redis
Requires-Dist: aio-pika (>=7) ; extra == "all" or extra == "rabbitmq"
Requires-Dist: aioboto3 (>=9.3) ; extra == "all" or extra == "ceph"
Requires-Dist: aiohttp[speedups] (>=3) ; extra == "all" or extra == "http"
Requires-Dist: asyncpg (>=0.25.0) ; extra == "all" or extra == "postgres"
Requires-Dist: fastapi (>=0.70.1)
Requires-Dist: pydantic (>=2.5)
Requires-Dist: pydantic-settings (>=2.1)
Requires-Dist: redis (>=4) ; extra == "all" or extra == "redis"
